stmlearn/__init__.py
stmlearn/equivalencecheckers/_AFLequivalencechecker.py
stmlearn/equivalencecheckers/_AFLequivalencecheckerV2.py
stmlearn/equivalencecheckers/__init__.py
stmlearn/equivalencecheckers/_bruteforce.py
stmlearn/equivalencecheckers/_equivalencechecker.py
stmlearn/equivalencecheckers/_genetic.py
stmlearn/equivalencecheckers/_libfuzzerequivalencechecker.py
stmlearn/equivalencecheckers/_markovequivalencechecker.py
stmlearn/equivalencecheckers/_mutationeqchecker.py
stmlearn/equivalencecheckers/_nusmv.py
stmlearn/equivalencecheckers/_randomwalk.py
stmlearn/equivalencecheckers/_stackedchecker.py
stmlearn/equivalencecheckers/_wmethod.py
stmlearn/learners/__init__.py
stmlearn/learners/_learner.py
stmlearn/learners/_lstar_dfa_learner.py
stmlearn/learners/_lstar_mealy_learner.py
stmlearn/learners/_ttt_abstract_learner.py
stmlearn/learners/_ttt_dfa_learner.py
stmlearn/learners/_ttt_mealy_learner.py
stmlearn/suls/__init__.py
stmlearn/suls/_dfa.py
stmlearn/suls/_mealy_machine.py
stmlearn/suls/_re_machine.py
stmlearn/suls/_rerssoconnector.py
stmlearn/suls/_sul.py
stmlearn/suls/caches/__init__.py
stmlearn/suls/caches/abscache.py
stmlearn/suls/caches/dictcache.py
stmlearn/suls/caches/rerstriecache.py
stmlearn/suls/caches/triecache.py
stmlearn/teachers/__init__.py
stmlearn/teachers/_teacher.py
stmlearn/util/_RNG.py
stmlearn/util/__init__.py
stmlearn/util/_dotloader.py
stmlearn/util/_editdistance.py
stmlearn/util/_fsmutil.py
stmlearn/util/_instrumentation.py
stmlearn/util/_markov.py
stmlearn/util/_mealy2nusmv.py
stmlearn/util/_mealygenerator.py
stmlearn/util/_mealytomcrl2.py
stmlearn/util/_notifier_set.py
stmlearn/util/_nusmv.py
stmlearn/util/_plotting.py
stmlearn/util/_product.py
stmlearn/util/_savehypothesis.py
stmlearn/util/_spot_ltl_translate.py
stmlearn/util/_transitioncover.py
stmlearn/util/stats.py
stmlearn/util/distinguishingset/__init__.py
stmlearn/util/distinguishingset/_distinguishingset.py
stmlearn/util/distinguishingset/_distinguishingset_fast.py
stmlearn-0.0.3.dist-info/LICENSE
stmlearn-0.0.3.dist-info/METADATA
stmlearn-0.0.3.dist-info/WHEEL
stmlearn-0.0.3.dist-info/top_level.txt
stmlearn-0.0.3.dist-info/RECORD
