Metadata-Version: 2.1
Name: stmlearn
Version: 0.0.3
Summary: Python state machine learning library
Home-page: https://github.com/TCatshoek/STMLearn
Author: T. Catshoek
Author-email: tomcatshoek@zeelandnet.nl
License: UNKNOWN
Platform: UNKNOWN
Classifier: Programming Language :: Python :: 3
Classifier: License :: OSI Approved :: GNU Lesser General Public License v3 (LGPLv3)
Classifier: Operating System :: POSIX :: Linux
Classifier: Development Status :: 3 - Alpha
Requires-Python: >=3.6
Requires-Dist: numpy
Requires-Dist: tabulate
Requires-Dist: graphviz
Requires-Dist: pygtrie
